decompress/__init__.py
decompress/util.py
decompress-0.0.5.dist-info/METADATA
decompress-0.0.5.dist-info/WHEEL
decompress-0.0.5.dist-info/top_level.txt
decompress-0.0.5.dist-info/RECORD
