Metadata-Version: 2.1
Name: decompress
Version: 0.0.5
Summary: A library to help decompress multiple compression types
Home-page: https://github.com/limeai/decompress
Author: Kevin Bird
Author-email: kevinbird15@gmail.com
License: UNKNOWN
Platform: UNKNOWN
Classifier: Programming Language :: Python :: 3
Classifier: License :: OSI Approved :: MIT License
Classifier: Operating System :: OS Independent
Requires-Python: >=3
